MANIFEST.in
requirements.txt
setup.py
sphinx_kml/__init__.py
sphinx_kml/google.html
sphinx_kml.egg-info/PKG-INFO
sphinx_kml.egg-info/SOURCES.txt
sphinx_kml.egg-info/dependency_links.txt
sphinx_kml.egg-info/pbr.json
sphinx_kml.egg-info/requires.txt
sphinx_kml.egg-info/top_level.txt