Metadata-Version: 1.1
Name: sphinx-kml
Version: 0.1.3
Summary: Embed maps in your Sphinx documents using a locally-stored KML file.
Home-page: https://github.com/coddingtonbear/sphinx-kml
Author: Adam Coddington
Author-email: me@adamcoddington.net
License: UNKNOWN
Platform: UNKNOWN
Classifier: License :: OSI Approved :: MIT License
Classifier: Operating System :: OS Independent
